sbom4files/__init__.py
sbom4files/cli.py
sbom4files/filescanner.py
sbom4files/version.py
sbom4files/filetypes/filetypes.txt
sbom4files-0.4.5.dist-info/LICENSE
sbom4files-0.4.5.dist-info/METADATA
sbom4files-0.4.5.dist-info/WHEEL
sbom4files-0.4.5.dist-info/entry_points.txt
sbom4files-0.4.5.dist-info/top_level.txt
sbom4files-0.4.5.dist-info/RECORD
